{"sections":{"main":{"type":"main-page","disabled":true,"custom_css":[],"settings":{"center":false}},"rich_text_PNhCnn":{"type":"rich-text","blocks":{"title_Gyamhx":{"type":"title","settings":{"title":"Rental Mattress Management","title_size":"h2","seo_h_tag":"h2"}},"text_ekbaaG":{"type":"text","settings":{"text":"<p>Manage your Rental Mattresses using our convenient Request Portal 24\/7.<\/p>","text_size":"large"}},"text_JbKK9V":{"type":"text","settings":{"text":"<p>Whether you need to put a <strong>Spare Mattress into Use<\/strong>, request a <strong>New Rental Mattress Delivery<\/strong>, or arrange a <strong>Rental Mattress Collection<\/strong>, your requirement will be directed to your dedicated Account Manager and processed to the highest level of customer service during our office hours, 9:00am–5:00pm.<br\/><br\/>Please select the option below that best matches your requirement. You will be directed to a form where you can submit your request.<\/p>","text_size":"regular"}},"button_kkDVMY":{"type":"button","disabled":true,"settings":{"button_label":"Rental Mattress Delivery","link":"https:\/\/devhub2024.myshopify.com\/pages\/rental-mattress-delivery","button_size":"large","button_style":"outline"}},"button_HKiBDh":{"type":"button","disabled":true,"settings":{"button_label":"Rental Mattress Collection","link":"https:\/\/devhub2024.myshopify.com\/pages\/rental-mattress-collection","button_size":"large","button_style":"outline"}},"button_HxKxFV":{"type":"button","disabled":true,"settings":{"button_label":"Rental Spare into Use","link":"https:\/\/devhub2024.myshopify.com\/pages\/rental-spare-into-use","button_size":"large","button_style":"outline"}}},"block_order":["title_Gyamhx","text_ekbaaG","text_JbKK9V","button_kkDVMY","button_HKiBDh","button_HxKxFV"],"custom_css":[".gutter--xlarge {padding: 0 !important;}",".text-size--large p {color: #8b83e2;}",".gutter--xlarge {padding: 0 !important;}",".card__text h2 {color: #350078; margin-top: 1em;}"],"settings":{"image_position":"top no-image","height":"small","image_crop":false,"text_alignment":"horizontal-left","is_fullwidth":false,"section_background_color":"rgba(0,0,0,0)","remove_margin":false,"color_background_main":"rgba(0,0,0,0)","color_text_main":"rgba(0,0,0,0)","color_accent_main":"rgba(0,0,0,0)","color_borders_main":"rgba(0,0,0,0)","color_shadow_main":"rgba(0,0,0,0)","color_hide_borders":true,"color_hide_shadow":true}},"e5d33890-e104-4507-b42a-a40303dc52ab":{"type":"promotion-cards","blocks":{"template--20503782687067__e5d33890-e104-4507-b42a-a40303dc52ab-card-1":{"type":"card","settings":{"caption":"Submit Request For","title":"Rental Spare into Use","subtitle":"","link":"shopify:\/\/pages\/spare-into-use","button_label":"Submit","color_background_main":"#c2bff3","color_text_main":"rgba(0,0,0,0)","color_accent_main":"rgba(0,0,0,0)","color_borders_main":"rgba(0,0,0,0)","color_shadow_main":"rgba(0,0,0,0)","color_hide_borders":true,"color_hide_shadow":false,"seo_h_tag":"h3"}},"template--20503782687067__e5d33890-e104-4507-b42a-a40303dc52ab-card-2":{"type":"card","settings":{"caption":"Submit Request For","title":"Rental Mattress Delivery","subtitle":"","link":"shopify:\/\/pages\/new-mattress-delivery","button_label":"Submit","color_background_main":"#99ded0","color_text_main":"rgba(0,0,0,0)","color_accent_main":"rgba(0,0,0,0)","color_borders_main":"rgba(0,0,0,0)","color_shadow_main":"rgba(0,0,0,0)","color_hide_borders":true,"color_hide_shadow":false,"seo_h_tag":"h3"}},"template--20503782687067__e5d33890-e104-4507-b42a-a40303dc52ab-card-3":{"type":"card","settings":{"caption":"Submit Request For","title":"Rental Mattress Collection","subtitle":"","link":"shopify:\/\/pages\/mattress-collection","button_label":"Submit","color_background_main":"#f8f1e4","color_text_main":"rgba(0,0,0,0)","color_accent_main":"rgba(0,0,0,0)","color_borders_main":"rgba(0,0,0,0)","color_shadow_main":"rgba(0,0,0,0)","color_hide_borders":true,"color_hide_shadow":false,"seo_h_tag":"h3"}}},"block_order":["template--20503782687067__e5d33890-e104-4507-b42a-a40303dc52ab-card-1","template--20503782687067__e5d33890-e104-4507-b42a-a40303dc52ab-card-2","template--20503782687067__e5d33890-e104-4507-b42a-a40303dc52ab-card-3"],"custom_css":[".card__text h3 {font-weight: 400;}",".button--outline:hover {background-color: #350078; border-color: #350078;}",".button--outline {color: #350078; border: 1px solid #350078;}",".button--outline:hover {color: #fff; background: #350078;}"],"settings":{"heading":"","subheading":"","section_heading_layout":"section-heading--left","layout":"grid-3 grid-lap-1","image_aspect_ratio":"1","text_alignment":"text-align--center","caption_size":"regular","title_size":"h3","subtitle_size":"regular","button_size":"large","button_style":"outline","section_background_color":"rgba(0,0,0,0)","section_heading_color":"rgba(0,0,0,0)","remove_margin":false,"seo_h_tag":"h2"}},"6e087eab-3dbe-4205-8598-6edc1efc119b":{"type":"rich-text","blocks":{"template--20503782687067__6e087eab-3dbe-4205-8598-6edc1efc119b-title-1":{"type":"title","settings":{"title":"Enhancing Patient Experiences","title_size":"h2","seo_h_tag":"h2"}},"text_37F7HA":{"type":"text","settings":{"text":"<p>You now have the opportunity to expand the range of equipment your facility has on site, ensuring you are always using the best-in-class equipment, and maintaining consistency in the patient experience. <\/p>","text_size":"large"}}},"block_order":["template--20503782687067__6e087eab-3dbe-4205-8598-6edc1efc119b-title-1","text_37F7HA"],"disabled":true,"custom_css":[".rich-text__title {font-weight: 400;}",".text-size--regular {color: #1d1d1d;}",".text-size--regular p {font-weight: 500;}",".spacing--large > *.increased-spacing {display: inline-block;}","@media only screen and (min-width: 768px) {.card__text {padding: 0; }}"],"settings":{"image":"shopify:\/\/shop_images\/Unsplash_Image_03A.png","image_position":"right","height":"small","image_crop":false,"text_alignment":"horizontal-left","is_fullwidth":false,"section_background_color":"rgba(0,0,0,0)","remove_margin":false,"color_background_main":"rgba(0,0,0,0)","color_text_main":"#350078","color_accent_main":"rgba(0,0,0,0)","color_borders_main":"rgba(0,0,0,0)","color_shadow_main":"rgba(0,0,0,0)","color_hide_borders":true,"color_hide_shadow":true}},"rich_text_VdwVn4":{"type":"rich-text","blocks":{"title_H7CMXh":{"type":"title","settings":{"title":"Ensuring Staff Satisfaction","title_size":"h2","seo_h_tag":"h2"}},"text_k9jnQ3":{"type":"text","settings":{"text":"<p>With access to the highest quality equipment in the market, your staff have that extra reassurance that their patients are being cared for with the best equipment. <br\/><br\/><\/p>","text_size":"large"}}},"block_order":["title_H7CMXh","text_k9jnQ3"],"disabled":true,"custom_css":[".rich-text__title {font-weight: 400;}",".text-size--regular {color: #1d1d1d;}",".text-size--regular p {font-weight: 500;}",".spacing--large > *.increased-spacing {display: inline-block;}","@media only screen and (min-width: 768px) {.card__text {padding: 0; }}"],"settings":{"image":"shopify:\/\/shop_images\/Unsplash_Image_01A_415fe0f0-5089-4412-81cb-02ee6470dd8c.png","image_position":"left","height":"small","image_crop":false,"text_alignment":"horizontal-left","is_fullwidth":false,"section_background_color":"rgba(0,0,0,0)","remove_margin":false,"color_background_main":"rgba(0,0,0,0)","color_text_main":"#350078","color_accent_main":"rgba(0,0,0,0)","color_borders_main":"rgba(0,0,0,0)","color_shadow_main":"rgba(0,0,0,0)","color_hide_borders":true,"color_hide_shadow":true}},"rich_text_VVEjBx":{"type":"rich-text","blocks":{"title_KQmKB6":{"type":"title","settings":{"title":"Simplifying Financial Planning","title_size":"h2","seo_h_tag":"h2"}},"text_TUKmU6":{"type":"text","settings":{"text":"<p>By renting your medical equipment, you can defer the full cost of the equipment, keeping more capital in-house. You can reduce costs by only paying for the equipment you need when you need it, and you have more control over your equipment budget. <\/p>","text_size":"large"}}},"block_order":["title_KQmKB6","text_TUKmU6"],"disabled":true,"custom_css":[".rich-text__title {font-weight: 400;}",".text-size--regular {color: #1d1d1d;}",".text-size--regular p {font-weight: 500;}",".spacing--large > *.increased-spacing {display: inline-block;}","@media only screen and (min-width: 768px) {.card__text {padding: 0; }}"],"settings":{"image":"shopify:\/\/shop_images\/Unsplash_Image_03A_1.png","image_position":"right","height":"small","image_crop":false,"text_alignment":"horizontal-left","is_fullwidth":false,"section_background_color":"rgba(0,0,0,0)","remove_margin":false,"color_background_main":"rgba(0,0,0,0)","color_text_main":"#350078","color_accent_main":"rgba(0,0,0,0)","color_borders_main":"rgba(0,0,0,0)","color_shadow_main":"rgba(0,0,0,0)","color_hide_borders":true,"color_hide_shadow":true}},"custom_liquid_mdm6g8":{"type":"custom-liquid","custom_css":[".h4 {font-size: 3em; color: #350078;}",".h5 {color: #350078;}"],"settings":{"custom_liquid":"<div class=\"container--large  container--vertical-space   remove-empty-space\"><div class=\"section-heading section-heading--center gutter-bottom--page\"><div class=\"section-heading__text remove-empty-space\"><h2 class=\"section-heading__title h4\">The benefits of using our rental service.<\/h2><\/div><\/div><style>\n    #shopify-section-template--22801860854107__text_columns_icons_JrYGKJ .card__icon {\n      border-radius: 200px;\n    }\n  <\/style><div class=\"rental-benefits-grid-container grid grid-3 grid-lap-2\"><div class=\"item item1 element--no-border text-align--center element--no-radius js-slider-item\">\n\n        <div class=\"card__icon card__icon--is-img card__icon-size--large lazyloaded\" id=\"element-image_FEjNby\"><img src=\"\/\/41895f-3.myshopify.com\/cdn\/shop\/files\/Vector.svg?crop=center&amp;height=64&amp;v=1716467236&amp;width=64\" alt=\"\" srcset=\"\n                \/\/41895f-3.myshopify.com\/cdn\/shop\/files\/Vector.svg?crop=center&amp;height=64&amp;v=1716467236&amp;width=64 64w\n                 \n                 \n                 \n              \" loading=\"lazy\" sizes=\"(max-width: 474px) 60px, (max-width: 1023px) 80px, 110px\" width=\"64\" height=\"64\" onload=\"this.parentNode.classList.add('lazyloaded')\"><\/div>\n\n        <div class=\"gutter--regular spacing--small remove-empty-space\"><div style=\"color:var(--color-text-main)\">\n              <h3 class=\"h5\" style=\"margin-bottom:0;display:block\"><span class=\"text-animation--underline\">Clinically-proven equipment<\/span><\/h3>\n            <\/div><div class=\"text-size--small text-color--opacity\" style=\"color:var(--color-text-main)\">We ensure all our equipment is clinically proven, safe &amp; effective.&nbsp;<\/div><\/div>\n      <\/div><style data-shopify=\"\">\n          #element-image_FEjNby {\n            background-color: #99ded0;\n          }\n        <\/style>\n<div class=\"item item2 element--no-border text-align--center element--no-radius js-slider-item\">\n\n        <div class=\"card__icon card__icon--is-img card__icon-size--large lazyloaded\" id=\"element-image_JqbY3W\"><img src=\"\/\/41895f-3.myshopify.com\/cdn\/shop\/files\/item-02.svg?crop=center&amp;height=64&amp;v=1716467288&amp;width=64\" alt=\"\" srcset=\"\n                \/\/41895f-3.myshopify.com\/cdn\/shop\/files\/item-02.svg?crop=center&amp;height=64&amp;v=1716467288&amp;width=64 64w\n                 \n                 \n                 \n              \" loading=\"lazy\" sizes=\"(max-width: 474px) 60px, (max-width: 1023px) 80px, 110px\" width=\"64\" height=\"64\" onload=\"this.parentNode.classList.add('lazyloaded')\"><\/div>\n\n        <div class=\"gutter--regular spacing--small remove-empty-space\"><div style=\"color:var(--color-text-main)\">\n              <h3 class=\"h5\" style=\"margin-bottom:0;display:block\"><span class=\"text-animation--underline\">Access to emergency replacements<\/span><\/h3>\n            <\/div><div class=\"text-size--small text-color--opacity\" style=\"color:var(--color-text-main)\">Immediate replacements when you need them, with no added repair or service costs.&nbsp;<\/div><\/div>\n      <\/div><style data-shopify=\"\">\n          #element-image_JqbY3W {\n            background-color: #f8f1e4;\n          }\n        <\/style>\n<div class=\"item item3 element--no-border text-align--center element--no-radius js-slider-item\">\n\n        <div class=\"card__icon card__icon--is-img card__icon-size--large lazyloaded\" id=\"element-image_NF8kdK\"><img src=\"\/\/41895f-3.myshopify.com\/cdn\/shop\/files\/item-03.svg?crop=center&amp;height=64&amp;v=1716467316&amp;width=64\" alt=\"\" srcset=\"\n                \/\/41895f-3.myshopify.com\/cdn\/shop\/files\/item-03.svg?crop=center&amp;height=64&amp;v=1716467316&amp;width=64 64w\n                 \n                 \n                 \n              \" loading=\"lazy\" sizes=\"(max-width: 474px) 60px, (max-width: 1023px) 80px, 110px\" width=\"64\" height=\"64\" onload=\"this.parentNode.classList.add('lazyloaded')\"><\/div>\n\n        <div class=\"gutter--regular spacing--small remove-empty-space\"><div style=\"color:var(--color-text-main)\">\n              <h3 class=\"h5\" style=\"margin-bottom:0;display:block\"><span class=\"text-animation--underline\">The highest standards of sterilization&nbsp;<\/span><\/h3>\n            <\/div><div class=\"text-size--small text-color--opacity\" style=\"color:var(--color-text-main)\">Using the highest quality infection control systems - Otex ozone infection control system.<\/div><\/div>\n      <\/div><style data-shopify=\"\">\n          #element-image_NF8kdK {\n            background-color: #ffdbd6;\n          }\n        <\/style>\n<div class=\"item item4 element--no-border text-align--center element--no-radius js-slider-item\">\n\n        <div class=\"card__icon card__icon--is-img card__icon-size--large lazyloaded\" id=\"element-image_aHhVWC\"><img src=\"\/\/41895f-3.myshopify.com\/cdn\/shop\/files\/item-04.svg?crop=center&amp;height=64&amp;v=1716467340&amp;width=64\" alt=\"\" srcset=\"\n                \/\/41895f-3.myshopify.com\/cdn\/shop\/files\/item-04.svg?crop=center&amp;height=64&amp;v=1716467340&amp;width=64 64w\n                 \n                 \n                 \n              \" loading=\"lazy\" sizes=\"(max-width: 474px) 60px, (max-width: 1023px) 80px, 110px\" width=\"64\" height=\"64\" onload=\"this.parentNode.classList.add('lazyloaded')\"><\/div>\n\n        <div class=\"gutter--regular spacing--small remove-empty-space\"><div style=\"color:var(--color-text-main)\">\n              <h3 class=\"h5\" style=\"margin-bottom:0;display:block\"><span class=\"text-animation--underline\">Trusted delivery partner<\/span><\/h3>\n            <\/div><div class=\"text-size--small text-color--opacity\" style=\"color:var(--color-text-main)\">All equipment will be delivered on time, every time.&nbsp;<\/div><\/div>\n      <\/div><style data-shopify=\"\">\n          #element-image_aHhVWC {\n            background-color: #ccd6d5;\n          }\n        <\/style>\n<div class=\"item item5 element--no-border text-align--center element--no-radius js-slider-item\">\n\n        <div class=\"card__icon card__icon--is-img card__icon-size--large lazyloaded\" id=\"element-image_yHcJcj\"><img src=\"\/\/41895f-3.myshopify.com\/cdn\/shop\/files\/item-05.svg?crop=center&amp;height=64&amp;v=1716467354&amp;width=64\" alt=\"\" srcset=\"\n                \/\/41895f-3.myshopify.com\/cdn\/shop\/files\/item-05.svg?crop=center&amp;height=64&amp;v=1716467354&amp;width=64 64w\n                 \n                 \n                 \n              \" loading=\"lazy\" sizes=\"(max-width: 474px) 60px, (max-width: 1023px) 80px, 110px\" width=\"64\" height=\"64\" onload=\"this.parentNode.classList.add('lazyloaded')\"><\/div>\n\n        <div class=\"gutter--regular spacing--small remove-empty-space\"><div style=\"color:var(--color-text-main)\">\n              <h3 class=\"h5\" style=\"margin-bottom:0;display:block\"><span class=\"text-animation--underline\">No minimum term requirements<\/span><\/h3>\n            <\/div><div class=\"text-size--small text-color--opacity\" style=\"color:var(--color-text-main)\">You have full control over the equipment rental agreements.<\/div><\/div>\n      <\/div><style data-shopify=\"\">\n          #element-image_yHcJcj {\n            background-color: #f8f1e4;\n          }\n        <\/style>\n\n\n  <\/div><\/div>","full_width":false,"remove_margin":false}},"custom_liquid_4g9dam":{"type":"custom-liquid","custom_css":["a {margin: 0 auto; display: block; width: max-content; background-color: #6ccfbd; color: #3c0077; border-color: #6ccfbd;}","a:hover {background-color: #3c0077; color: #fff; border-color: #3c0077;}"],"settings":{"custom_liquid":"<a class=\"solid-green button button--large button--outline\" href=\"#\">Enquire Now<\/a>","full_width":false,"remove_margin":false}},"collection_list_yjFbaL":{"type":"collection-list","blocks":{"collection_UARLac":{"type":"collection","settings":{"collection":"beds"}},"collection_6wQfTy":{"type":"collection","settings":{"collection":"wheelchairs"}},"collection_E3xqNN":{"type":"collection","settings":{"collection":"hoists"}},"collection_P8WVPE":{"type":"collection","settings":{"collection":"bariatric"}},"collection_kBWhy8":{"type":"collection","settings":{"collection":"mattresses-cushions"}},"collection_8PPkXn":{"type":"collection","settings":{"collection":"commodes"}},"collection_rRQtLg":{"type":"collection","settings":{"collection":"chairs"}},"collection_gf76c6":{"type":"collection","settings":{"collection":"scooters"}}},"block_order":["collection_UARLac","collection_6wQfTy","collection_E3xqNN","collection_P8WVPE","collection_kBWhy8","collection_8PPkXn","collection_rRQtLg","collection_gf76c6"],"settings":{"heading":"Featured collections","subheading":"","show_view_all":true,"section_heading_layout":"section-heading--left","style":"slider","layout":"grid-6 grid-portable-4 grid-lap-3 grid-palm-2","image_aspect_ratio":"1","section_background_color":"rgba(0,0,0,0)","section_heading_color":"rgba(0,0,0,0)","remove_margin":false,"seo_h_tag":"h2"}},"text_columns_icons_pPWbm4":{"type":"text-columns-icons","blocks":{"image_8RXX9k":{"type":"image","settings":{"icon":"delivery","image":"shopify:\/\/shop_images\/hospitals.svg","title":"Hospitals","caption":"","link":"","color_background_main":"rgba(0,0,0,0)","color_icons_main":"rgba(0,0,0,0)","seo_h_tag":"h3"}},"image_gYcLEB":{"type":"image","settings":{"icon":"time-limit","image":"shopify:\/\/shop_images\/nursing-homes.svg","title":"Nursing Homes","caption":"","link":"","color_background_main":"rgba(0,0,0,0)","color_icons_main":"rgba(0,0,0,0)","seo_h_tag":"h3"}},"image_GjFdqq":{"type":"image","settings":{"icon":"store","image":"shopify:\/\/shop_images\/private-homes_62d3f23d-d339-4a48-9e67-dc0525b16b07.svg","title":"Private Homes","caption":"","link":"","color_background_main":"rgba(0,0,0,0)","color_icons_main":"rgba(0,0,0,0)","seo_h_tag":"h3"}},"image_9aVWRc":{"type":"image","settings":{"icon":"tree","image":"shopify:\/\/shop_images\/hotels.svg","title":"Hotels","caption":"","link":"","color_background_main":"rgba(0,0,0,0)","color_icons_main":"rgba(0,0,0,0)","seo_h_tag":"h3"}}},"block_order":["image_8RXX9k","image_gYcLEB","image_GjFdqq","image_9aVWRc"],"custom_css":[".text-size--small {color: #333333 !important; opacity: 0.8;}","@media screen and (min-width: 1024px) {h4, .h4 {font-size: 3em; }}"],"settings":{"heading":"","subheading":"","section_heading_layout":"section-heading--center","style":"grid","layout":"grid-4 grid-portable-3 grid-lap-2","border_radius":200,"section_background_color":"rgba(0,0,0,0)","section_heading_color":"#350078","remove_margin":false,"seo_h_tag":"h2"}},"7b9111ef-1ea7-4f3e-b325-0928e395f195":{"type":"media-with-text-overlay","blocks":{"template--20503782687067__7b9111ef-1ea7-4f3e-b325-0928e395f195-image-1":{"type":"image","settings":{"image":"shopify:\/\/shop_images\/home-banner-1.jpg","caption":"INCONTINENCE","title":"Having the confidence to be comfortably you.","subtitle":"","link":"shopify:\/\/collections\/incontinence","button_label":"View products","color_background_main":"rgba(0,0,0,0)","color_text_main":"rgba(0,0,0,0)","color_hide_borders":false,"color_hide_shadow":false,"seo_h_tag":"h3"}},"template--20503782687067__7b9111ef-1ea7-4f3e-b325-0928e395f195-image-2":{"type":"image","settings":{"image":"shopify:\/\/shop_images\/home-banner-2.jpg","caption":"BEDS","title":"Rediscover yourself with a good night’s rest.","subtitle":"","link":"shopify:\/\/collections\/beds","button_label":"View products","color_background_main":"rgba(0,0,0,0)","color_text_main":"rgba(0,0,0,0)","color_hide_borders":true,"color_hide_shadow":true,"seo_h_tag":"h3"}}},"block_order":["template--20503782687067__7b9111ef-1ea7-4f3e-b325-0928e395f195-image-1","template--20503782687067__7b9111ef-1ea7-4f3e-b325-0928e395f195-image-2"],"disabled":true,"custom_css":[".card {display: flex; flex-direction: column;}",".card .card__text {order: 2; max-width: max-content;}",".card .card-image {order: 1 !important;}",".card__image--background {position: relative;}",".lazy-image.lazy-image--background {padding-top: unset !important; position: relative !important;}",".lazy-image[data-ratio] img {position: relative;}",".h3 {font-weight: 400;}"],"settings":{"heading":"","subheading":"","section_heading_layout":"section-heading--left","layout":"grid-2 grid-lap-1","height":"regular","alignment":"horizontal-left align-content--vertical-bottom","width":"60%","caption_size":"small","title_size":"h3","subtitle_size":"regular","button_size":"regular","button_style":"outline","section_background_color":"rgba(0,0,0,0)","section_heading_color":"rgba(0,0,0,0)","remove_margin":false,"seo_h_tag":"h2"}},"rich_text_yKJmgd":{"type":"rich-text","blocks":{"title_zKNV9Y":{"type":"title","settings":{"title":"Quality, Assured.","title_size":"h2","seo_h_tag":"h2"}},"text_br8KPn":{"type":"text","settings":{"text":"<p>We pride ourselves in offering the optimum customer service, with a very strong emphasis on quality. We are proud holder of the following ISO certifications.<\/p>","text_size":"regular"}},"text_mfx6n9":{"type":"text","settings":{"text":"<p><a href=\"#\" title=\"#\">ISO 9001 (Quality Management Systems) <\/a><\/p><p><a href=\"#\" title=\"#\">ISO 14001 (Environmental Management System)<\/a> <\/p><p><a href=\"#\" title=\"#\">ISO 13485 (Medical Devices Quality Management Systems)<\/a><\/p>","text_size":"regular"}}},"block_order":["title_zKNV9Y","text_br8KPn","text_mfx6n9"],"custom_css":[".text-size--regular p a {color: #350078;}"],"settings":{"image_position":"left","height":"small","image_crop":false,"text_alignment":"horizontal-left","is_fullwidth":false,"section_background_color":"rgba(0,0,0,0)","remove_margin":false,"color_background_main":"rgba(0,0,0,0)","color_text_main":"rgba(0,0,0,0)","color_accent_main":"rgba(0,0,0,0)","color_borders_main":"rgba(0,0,0,0)","color_shadow_main":"rgba(0,0,0,0)","color_hide_borders":true,"color_hide_shadow":true}}},"order":["main","rich_text_PNhCnn","e5d33890-e104-4507-b42a-a40303dc52ab","6e087eab-3dbe-4205-8598-6edc1efc119b","rich_text_VdwVn4","rich_text_VVEjBx","custom_liquid_mdm6g8","custom_liquid_4g9dam","collection_list_yjFbaL","text_columns_icons_pPWbm4","7b9111ef-1ea7-4f3e-b325-0928e395f195","rich_text_yKJmgd"]}